pybasedb
