Metadata-Version: 2.1
Name: pyBaseDB
Version: 0.2.7
Summary: Python built NoSQL database
Home-page: UNKNOWN
Author: Carlos Silva
Author-email: carlos.miguel.silva@protonmail.com
License: MIT
Platform: UNKNOWN
Classifier: Development Status :: 4 - Beta
Classifier: Intended Audience :: Developers
Classifier: Topic :: Software Development
Classifier: Programming Language :: Python :: 3
Classifier: License :: OSI Approved :: MIT License
Classifier: Operating System :: OS Independent
Requires-Python: >=3.8
